[{"id":"http://www.wikidata.org/entity/Q1406","name":"Microsoft Windows"},{"id":"http://www.wikidata.org/entity/Q94","name":"Android"},{"id":"http://www.wikidata.org/entity/Q8079","name":"Wii"},{"id":"http://www.wikidata.org/entity/Q388","name":"Linux"},{"id":"http://www.wikidata.org/entity/Q23882","name":"ZX Spectrum"},{"id":"http://www.wikidata.org/entity/Q10680","name":"PlayStation 2"},{"id":"http://www.wikidata.org/entity/Q10683","name":"PlayStation 3"},{"id":"http://www.wikidata.org/entity/Q10676","name":"Sega Genesis"},{"id":"http://www.wikidata.org/entity/Q99775","name":"Commodore 64"},{"id":"http://www.wikidata.org/entity/Q48493","name":"iOS"},{"id":"http://www.wikidata.org/entity/Q48263","name":"Xbox 360"},{"id":"http://www.wikidata.org/entity/Q100047","name":"Commodore Amiga"},{"id":"http://www.wikidata.org/entity/Q170323","name":"Nintendo DS"},{"id":"http://www.wikidata.org/entity/Q132020","name":"Xbox"},{"id":"http://www.wikidata.org/entity/Q170325","name":"PlayStation Portable"},{"id":"http://www.wikidata.org/entity/Q170434","name":"DOS"},{"id":"http://www.wikidata.org/entity/Q135321","name":"Family Computer Disk System"},{"id":"http://www.wikidata.org/entity/Q6368","name":"web browser"},{"id":"http://www.wikidata.org/entity/Q172742","name":"Nintendo Entertainment System"},{"id":"http://www.wikidata.org/entity/Q183259","name":"Super Nintendo Entertainment System"},{"id":"http://www.wikidata.org/entity/Q10677","name":"PlayStation"},{"id":"http://www.wikidata.org/entity/Q186437","name":"Game Boy"},{"id":"http://www.wikidata.org/entity/Q188642","name":"Game Boy Advance"},{"id":"http://www.wikidata.org/entity/Q183505","name":"NEC PC-9800 series"},{"id":"http://www.wikidata.org/entity/Q342163","name":"Acorn Electron"},{"id":"http://www.wikidata.org/entity/Q206261","name":"Atari 2600"},{"id":"http://www.wikidata.org/entity/Q203992","name":"Game Boy Color"},{"id":"http://www.wikidata.org/entity/Q200912","name":"Sega Saturn"},{"id":"http://www.wikidata.org/entity/Q192851","name":"arcade video game machine"},{"id":"http://www.wikidata.org/entity/Q478829","name":"Amstrad CPC"},{"id":"http://www.wikidata.org/entity/Q14116","name":"macOS"},{"id":"http://www.wikidata.org/entity/Q249075","name":"Atari 8-bit family"},{"id":"http://www.wikidata.org/entity/Q627302","name":"Atari ST"},{"id":"http://www.wikidata.org/entity/Q209868","name":"Sega Master System"},{"id":"http://www.wikidata.org/entity/Q531896","name":"FM Towns"},{"id":"http://www.wikidata.org/entity/Q749976","name":"BBC Micro"},{"id":"http://www.wikidata.org/entity/Q743222","name":"Atari 5200"},{"id":"http://www.wikidata.org/entity/Q29758","name":"Pocket PC"},{"id":"http://www.wikidata.org/entity/Q31087","name":"calculator"},{"id":"http://www.wikidata.org/entity/Q16338","name":"personal computer"},{"id":"http://www.wikidata.org/entity/Q47604","name":"MS-DOS"},{"id":"http://www.wikidata.org/entity/Q41357","name":"Acorn Archimedes"},{"id":"http://www.wikidata.org/entity/Q21207","name":"Windows Mobile"},{"id":"http://www.wikidata.org/entity/Q868568","name":"Commodore Plus/4"},{"id":"http://www.wikidata.org/entity/Q821067","name":"Virtual Console"},{"id":"http://www.wikidata.org/entity/Q853547","name":"MSX"},{"id":"http://www.wikidata.org/entity/Q1282269","name":"Apple IIGS"},{"id":"http://www.wikidata.org/entity/Q1115913","name":"Commodore 16"},{"id":"http://www.wikidata.org/entity/Q1136956","name":"SG-1000"},{"id":"http://www.wikidata.org/entity/Q1887775","name":"Thomson TO7"},{"id":"http://www.wikidata.org/entity/Q2396081","name":"Thomson MO5"},{"id":"http://www.wikidata.org/entity/Q1046862","name":"ColecoVision"},{"id":"http://www.wikidata.org/entity/Q1057377","name":"TurboGrafx-16"},{"id":"http://www.wikidata.org/entity/Q56942","name":"Wii U"},{"id":"http://www.wikidata.org/entity/Q17517","name":"mobile phone"},{"id":"http://www.wikidata.org/entity/Q751719","name":"Game Gear"},{"id":"http://www.wikidata.org/entity/Q753657","name":"Atari Lynx"},{"id":"http://www.wikidata.org/entity/Q3017175","name":"Apple II"},{"id":"http://www.wikidata.org/entity/Q3095025","name":"MOTO Gamme"},{"id":"http://www.wikidata.org/entity/Q5014725","name":"PlayStation 4"},{"id":"http://www.wikidata.org/entity/Q1338888","name":"NEC PC-8800 series"},{"id":"http://www.wikidata.org/entity/Q13522376","name":"Classic Mac OS"},{"id":"http://www.wikidata.org/entity/Q12746387","name":"Olivetti Prodest PC 128"},{"id":"http://www.wikidata.org/entity/Q171819","name":"BlackBerry"},{"id":"http://www.wikidata.org/entity/Q178794","name":"watch"},{"id":"http://www.wikidata.org/entity/Q201652","name":"Apple II series"},{"id":"http://www.wikidata.org/entity/Q188808","name":"PlayStation Vita"},{"id":"http://www.wikidata.org/entity/Q215034","name":"Game & Watch series"},{"id":"http://www.wikidata.org/entity/Q225009","name":"Pandora"},{"id":"http://www.wikidata.org/entity/Q182172","name":"Nintendo GameCube"},{"id":"http://www.wikidata.org/entity/Q203597","name":"Nintendo 3DS"},{"id":"http://www.wikidata.org/entity/Q454390","name":"Texas Instruments TI-99/4A"},{"id":"http://www.wikidata.org/entity/Q471094","name":"Amiga 1200"},{"id":"http://www.wikidata.org/entity/Q202712","name":"IBM Personal Computer"},{"id":"http://www.wikidata.org/entity/Q229429","name":"3DO Interactive Multiplayer"},{"id":"http://www.wikidata.org/entity/Q380526","name":"AmigaOS"},{"id":"http://www.wikidata.org/entity/Q184198","name":"Dreamcast"},{"id":"http://www.wikidata.org/entity/Q918232","name":"Commodore VIC-20"},{"id":"http://www.wikidata.org/entity/Q954124","name":"Coleco"},{"id":"http://www.wikidata.org/entity/Q483318","name":"Symbian"},{"id":"http://www.wikidata.org/entity/Q753600","name":"Atari 7800"},{"id":"http://www.wikidata.org/entity/Q1993197","name":"Nintendo e-Reader"},{"id":"http://www.wikidata.org/entity/Q184839","name":"Nintendo 64"},{"id":"http://www.wikidata.org/entity/Q13361286","name":"Xbox One"},{"id":"http://www.wikidata.org/entity/Q19610114","name":"Nintendo Switch"},{"id":"http://www.wikidata.org/entity/Q1061441","name":"Intellivision"},{"id":"http://www.wikidata.org/entity/Q1391641","name":"Ouya"},{"id":"http://www.wikidata.org/entity/Q336434","name":"N-Gage"},{"id":"http://www.wikidata.org/entity/Q98973368","name":"Xbox Series X and Series S"},{"id":"http://www.wikidata.org/entity/Q63184502","name":"PlayStation 5"},{"id":"http://www.wikidata.org/entity/Q695161","name":"Amiga CD32"},{"id":"http://www.wikidata.org/entity/Q880016","name":"BlackBerry OS"},{"id":"http://www.wikidata.org/entity/Q650601","name":"Atari Jaguar"},{"id":"http://www.wikidata.org/entity/Q646795","name":"MorphOS"},{"id":"http://www.wikidata.org/entity/Q1202514","name":"RISC OS"},{"id":"http://www.wikidata.org/entity/Q1349717","name":"arcade cabinet"},{"id":"http://www.wikidata.org/entity/Q1574899","name":"Atari TOS"},{"id":"http://www.wikidata.org/entity/Q4885200","name":"Windows Phone"},{"id":"http://www.wikidata.org/entity/Q43627","name":"Macintosh operating systems"},{"id":"http://www.wikidata.org/entity/Q753619","name":"Atari Falcon"},{"id":"http://www.wikidata.org/entity/Q184372","name":"Zeebo"},{"id":"http://www.wikidata.org/entity/Q1054350","name":"Neo Geo"},{"id":"http://www.wikidata.org/entity/Q174666","name":"cross-platform"},{"id":"http://www.wikidata.org/entity/Q1259157","name":"HP 3000"},{"id":"http://www.wikidata.org/entity/Q1758277","name":"Sharp X68000"},{"id":"http://www.wikidata.org/entity/Q75687","name":"Mac"},{"id":"http://www.wikidata.org/entity/Q14656","name":"Unix-like operating system"},{"id":"http://www.wikidata.org/entity/Q202375","name":"PC Engine SuperGrafx"},{"id":"http://www.wikidata.org/entity/Q352591","name":"Atari Panther"},{"id":"http://www.wikidata.org/entity/Q667808","name":"Motorola 68000"},{"id":"http://www.wikidata.org/entity/Q14918005","name":"PlayStation TV"},{"id":"http://www.wikidata.org/entity/Q263250","name":"Sinclair ZX81"},{"id":"http://www.wikidata.org/entity/Q1797918","name":"handheld electronic game"},{"id":"http://www.wikidata.org/entity/Q2416874","name":"Pelican VG Pocket"},{"id":"http://www.wikidata.org/entity/Q1065792","name":"WonderSwan"},{"id":"http://www.wikidata.org/entity/Q1121542","name":"mobile game"},{"id":"http://www.wikidata.org/entity/Q751046","name":"IBM PC compatible"},{"id":"http://www.wikidata.org/entity/Q5249798","name":"dedicated console"},{"id":"http://www.wikidata.org/entity/Q879989","name":"BlackBerry 10"},{"id":"http://www.wikidata.org/entity/Q1063978","name":"Sega 32X"},{"id":"http://www.wikidata.org/entity/Q1047516","name":"Sega CD"},{"id":"http://www.wikidata.org/entity/Q11703697","name":"Sega X Board"},{"id":"http://www.wikidata.org/entity/Q165658","name":"Adobe Flash"},{"id":"http://www.wikidata.org/entity/Q2379925","name":"FM-7"},{"id":"http://www.wikidata.org/entity/Q2710884","name":"Sharp X1"},{"id":"http://www.wikidata.org/entity/Q108148546","name":"TGP Box"},{"id":"http://www.wikidata.org/entity/Q637178","name":"Nintendo DSi"},{"id":"http://www.wikidata.org/entity/Q2703883","name":"Neo Geo CD"},{"id":"http://www.wikidata.org/entity/Q744171","name":"OnLive"},{"id":"http://www.wikidata.org/entity/Q177234","name":"mainframe computer"},{"id":"http://www.wikidata.org/entity/Q909092","name":"Nintendo Super System"},{"id":"http://www.wikidata.org/entity/Q1761667","name":"Apple IIe"},{"id":"http://www.wikidata.org/entity/Q14646","name":"Solaris"},{"id":"http://www.wikidata.org/entity/Q62563","name":"BeOS"},{"id":"http://www.wikidata.org/entity/Q164651","name":"Virtual Boy"},{"id":"http://www.wikidata.org/entity/Q189794","name":"OS/2"},{"id":"http://www.wikidata.org/entity/Q193321","name":"Java Virtual Machine"},{"id":"http://www.wikidata.org/entity/Q627611","name":"IRIX"},{"id":"http://www.wikidata.org/entity/Q831367","name":"NeXTSTEP"},{"id":"http://www.wikidata.org/entity/Q1353312","name":"RiscPC"},{"id":"http://www.wikidata.org/entity/Q1713118","name":"Java platform"},{"id":"http://www.wikidata.org/entity/Q2447314","name":"N-Gage"},{"id":"http://www.wikidata.org/entity/Q193828","name":"Java Platform, Micro Edition"},{"id":"http://www.wikidata.org/entity/Q113245462","name":"Flipper Zero"},{"id":"http://www.wikidata.org/entity/Q1023103","name":"Philips CD-i"},{"id":"http://www.wikidata.org/entity/Q203315","name":"Zilog Z80"},{"id":"http://www.wikidata.org/entity/Q355","name":"Facebook"},{"id":"http://www.wikidata.org/entity/Q1188778","name":"SAM Coupé"},{"id":"http://www.wikidata.org/entity/Q1759524","name":"Tatung Einstein"},{"id":"http://www.wikidata.org/entity/Q1115919","name":"Commodore 128"},{"id":"http://www.wikidata.org/entity/Q1088832","name":"PowerPC 600"},{"id":"http://www.wikidata.org/entity/Q767631","name":"Vectrex"},{"id":"http://www.wikidata.org/entity/Q255528","name":"MOS Technology 6502"},{"id":"http://www.wikidata.org/entity/Q841252","name":"TurboDuo"},{"id":"http://www.wikidata.org/entity/Q245","name":"Raspberry Pi"},{"id":"http://www.wikidata.org/entity/Q1136902","name":"PC-FX"},{"id":"http://www.wikidata.org/entity/Q285025","name":"iQue Player"},{"id":"http://www.wikidata.org/entity/Q143298","name":"Kindle Fire HD"},{"id":"http://www.wikidata.org/entity/Q79531","name":"ChromeOS"},{"id":"http://www.wikidata.org/entity/Q270285","name":"Apple TV"},{"id":"http://www.wikidata.org/entity/Q16203668","name":"Amazon Fire TV"},{"id":"http://www.wikidata.org/entity/Q17679679","name":"New Nintendo 3DS"},{"id":"http://www.wikidata.org/entity/Q4252","name":"Mii"},{"id":"http://www.wikidata.org/entity/Q610305","name":"TRS-80 Model I"},{"id":"http://www.wikidata.org/entity/Q1238768","name":"Dragon 32/64"},{"id":"http://www.wikidata.org/entity/Q170073","name":"Xbox network"},{"id":"http://www.wikidata.org/entity/Q3625572","name":"Facebook Platform"},{"id":"http://www.wikidata.org/entity/Q848991","name":"browser game"},{"id":"http://www.wikidata.org/entity/Q68","name":"computer"},{"id":"http://www.wikidata.org/entity/Q114712511","name":"Gameband"},{"id":"http://www.wikidata.org/entity/Q737508","name":"Windows 3.x"},{"id":"http://www.wikidata.org/entity/Q863516","name":"Binary Runtime Environment for Wireless"},{"id":"http://www.wikidata.org/entity/Q955368","name":"CDTV"},{"id":"http://www.wikidata.org/entity/Q1755406","name":"PLATO"},{"id":"http://www.wikidata.org/entity/Q1616633","name":"HP 2100"},{"id":"http://www.wikidata.org/entity/Q1758866","name":"PDP-1"},{"id":"http://www.wikidata.org/entity/Q478833","name":"Amstrad PCW"},{"id":"http://www.wikidata.org/entity/Q471144","name":"Amiga 4000"},{"id":"http://www.wikidata.org/entity/Q3870048","name":"Namco Galaga"},{"id":"http://www.wikidata.org/entity/Q62603091","name":"Mega Drive Mini"},{"id":"http://www.wikidata.org/entity/Q30827691","name":"Super NES Classic Edition"},{"id":"http://www.wikidata.org/entity/Q3491676","name":"Hitachi 6309"},{"id":"http://www.wikidata.org/entity/Q18845397","name":"Windows 10 Mobile"},{"id":"http://www.wikidata.org/entity/Q631229","name":"arcade system board"},{"id":"http://www.wikidata.org/entity/Q14094","name":"iPod Touch"},{"id":"http://www.wikidata.org/entity/Q863565","name":"Electronic Delay Storage Automatic Calculator"},{"id":"http://www.wikidata.org/entity/Q2881951","name":"Apricot PC"},{"id":"http://www.wikidata.org/entity/Q219528","name":"CP/M"},{"id":"http://www.wikidata.org/entity/Q308993","name":"NeXT"},{"id":"http://www.wikidata.org/entity/Q33972","name":"slot machine"},{"id":"http://www.wikidata.org/entity/Q747478","name":"Java Platform, Standard Edition"},{"id":"http://www.wikidata.org/entity/Q5384021","name":"Epson QX-10"},{"id":"http://www.wikidata.org/entity/Q1115981","name":"Commodore MAX Machine"},{"id":"http://www.wikidata.org/entity/Q11950733","name":"TRS-80 Color Computer 3"},{"id":"http://www.wikidata.org/entity/Q1977455","name":"Neo Geo Pocket Color"},{"id":"http://www.wikidata.org/entity/Q10269192","name":"Dynavision"},{"id":"http://www.wikidata.org/entity/Q1545600","name":"Motorola 6809"},{"id":"http://www.wikidata.org/entity/Q609733","name":"Windows 9x"},{"id":"http://www.wikidata.org/entity/Q379965","name":"Entex Adventure Vision"},{"id":"http://www.wikidata.org/entity/Q946661","name":"Commodore PET"},{"id":"http://www.wikidata.org/entity/Q1129603","name":"Osborne 1"},{"id":"http://www.wikidata.org/entity/Q1419081","name":"PC booter"},{"id":"http://www.wikidata.org/entity/Q21600523","name":"Universal Windows Platform"},{"id":"http://www.wikidata.org/entity/Q2053","name":"HTML5"},{"id":"http://www.wikidata.org/entity/Q12746424","name":"Oric Atmos"},{"id":"http://www.wikidata.org/entity/Q483881","name":"Windows 2000"},{"id":"http://www.wikidata.org/entity/Q388384","name":"Sega Mega-Tech"},{"id":"http://www.wikidata.org/entity/Q56513496","name":"Donner Model 30"},{"id":"http://www.wikidata.org/entity/Q17623231","name":"Shield Tablet"},{"id":"http://www.wikidata.org/entity/Q19605735","name":"Nvidia Shield TV"},{"id":"http://www.wikidata.org/entity/Q27076301","name":"Shield Portable"},{"id":"http://www.wikidata.org/entity/Q262238","name":"IA-32"},{"id":"http://www.wikidata.org/entity/Q15015195","name":"Apple Pippin"},{"id":"http://www.wikidata.org/entity/Q880005","name":"BlackBerry PlayBook"},{"id":"http://www.wikidata.org/entity/Q777","name":"Google Chrome"},{"id":"http://www.wikidata.org/entity/Q34215","name":"OpenBSD"},{"id":"http://www.wikidata.org/entity/Q34225","name":"NetBSD"},{"id":"http://www.wikidata.org/entity/Q34236","name":"FreeBSD"},{"id":"http://www.wikidata.org/entity/Q7715973","name":"Debian"},{"id":"http://www.wikidata.org/entity/Q60407","name":"PV-1000"},{"id":"http://www.wikidata.org/entity/Q2372633","name":"Zune HD"},{"id":"http://www.wikidata.org/entity/Q3922240","name":"BlackBerry Z10"},{"id":"http://www.wikidata.org/entity/Q3783103","name":"DVD player"},{"id":"http://www.wikidata.org/entity/Q904697","name":"Model 1"},{"id":"http://www.wikidata.org/entity/Q11232203","name":"MSX 2"},{"id":"http://www.wikidata.org/entity/Q166841","name":"Sharp Zaurus"},{"id":"http://www.wikidata.org/entity/Q15089879","name":"Fire OS"},{"id":"http://www.wikidata.org/entity/Q370601","name":"PlayChoice-10"},{"id":"http://www.wikidata.org/entity/Q26706777","name":"NES Classic Edition"},{"id":"http://www.wikidata.org/entity/Q442891","name":"Namco System 11"},{"id":"http://www.wikidata.org/entity/Q3458976","name":"S!Appli"},{"id":"http://www.wikidata.org/entity/Q11224960","name":"i-αppli"},{"id":"http://www.wikidata.org/entity/Q113726751","name":"arcade game"},{"id":"http://www.wikidata.org/entity/Q1411846","name":"TRS-80 Color Computer"},{"id":"http://www.wikidata.org/entity/Q64350339","name":"iPadOS"},{"id":"http://www.wikidata.org/entity/Q19599580","name":"Series 30+"},{"id":"http://www.wikidata.org/entity/Q2739670","name":"Atari Jaguar CD"},{"id":"http://www.wikidata.org/entity/Q237757","name":"Pentium 4"},{"id":"http://www.wikidata.org/entity/Q576932","name":"Magnavox Odyssey²"},{"id":"http://www.wikidata.org/entity/Q7185533","name":"Philips Videopac+ G7400"},{"id":"http://www.wikidata.org/entity/Q7273280","name":"R-Zone"},{"id":"http://www.wikidata.org/entity/Q208305","name":"Commodore International"},{"id":"http://www.wikidata.org/entity/Q3306898","name":"Atari 400"},{"id":"http://www.wikidata.org/entity/Q4889765","name":"Atari 800"},{"id":"http://www.wikidata.org/entity/Q989875","name":"Enterprise"},{"id":"http://www.wikidata.org/entity/Q976968","name":"PC-6600 series"},{"id":"http://www.wikidata.org/entity/Q1854071","name":"Sharp MZ"},{"id":"http://www.wikidata.org/entity/Q11232214","name":"MSX TurboR"},{"id":"http://www.wikidata.org/entity/Q1024934","name":"Motorola 68010"},{"id":"http://www.wikidata.org/entity/Q1374482","name":"Sega Pico"},{"id":"http://www.wikidata.org/entity/Q1270176","name":"PDP-7"},{"id":"http://www.wikidata.org/entity/Q1501565","name":"General Comprehensive Operating System"},{"id":"http://www.wikidata.org/entity/Q739186","name":"Multics"},{"id":"http://www.wikidata.org/entity/Q939881","name":"Neo Geo Pocket"},{"id":"http://www.wikidata.org/entity/Q7682528","name":"Tandy Video Information System"},{"id":"http://www.wikidata.org/entity/Q2440971","name":"PC-6000 series"},{"id":"http://www.wikidata.org/entity/Q2014637","name":"WiiWare"},{"id":"http://www.wikidata.org/entity/Q12058183","name":"TMS34010"},{"id":"http://www.wikidata.org/entity/Q844552","name":"Nintendo DS Lite"},{"id":"http://www.wikidata.org/entity/Q1048035","name":"WonderSwan Color"},{"id":"http://www.wikidata.org/entity/Q1143494","name":"DECO Cassette System"},{"id":"http://www.wikidata.org/entity/Q1190117","name":"Super Game Boy"},{"id":"http://www.wikidata.org/entity/Q19354826","name":"Nintendo 3DS family"},{"id":"http://www.wikidata.org/entity/Q207922","name":"Atari"},{"id":"http://www.wikidata.org/entity/Q3415008","name":"R4600"},{"id":"http://www.wikidata.org/entity/Q55438725","name":"Tomahawk F1"},{"id":"http://www.wikidata.org/entity/Q7820426","name":"Tomy Tutor"},{"id":"http://www.wikidata.org/entity/Q1758399","name":"PlayStation Home"},{"id":"http://www.wikidata.org/entity/Q1034233","name":"CP System"},{"id":"http://www.wikidata.org/entity/Q923987","name":"FM Towns Marty"},{"id":"http://www.wikidata.org/entity/Q3317075","name":"Mitchell"},{"id":"http://www.wikidata.org/entity/Q242157","name":"Bada"},{"id":"http://www.wikidata.org/entity/Q305873","name":"webOS"},{"id":"http://www.wikidata.org/entity/Q64428080","name":"Neo Geo AES"},{"id":"http://www.wikidata.org/entity/Q3338058","name":"Neo-Geo MVS"},{"id":"http://www.wikidata.org/entity/Q3356274","name":"Oric-1"},{"id":"http://www.wikidata.org/entity/Q76135548","name":"Commodore 16 and Plus/4"},{"id":"http://www.wikidata.org/entity/Q1193565","name":"Satellaview"},{"id":"http://www.wikidata.org/entity/Q970428","name":"list of DSiWare games and applications"},{"id":"http://www.wikidata.org/entity/Q253044","name":"64DD"},{"id":"http://www.wikidata.org/entity/Q10928179","name":"online and offline"},{"id":"http://www.wikidata.org/entity/Q112224827","name":"Mega Drive Mini 2"},{"id":"http://www.wikidata.org/entity/Q384656","name":"Amiga 500"},{"id":"http://www.wikidata.org/entity/Q55315688","name":"Thomson TO"},{"id":"http://www.wikidata.org/entity/Q3027757","name":"DigiBLAST"},{"id":"http://www.wikidata.org/entity/Q207539","name":"Intel 8086"},{"id":"http://www.wikidata.org/entity/Q474334","name":"Kinect"},{"id":"http://www.wikidata.org/entity/Q2981666","name":"CP System II"},{"id":"http://www.wikidata.org/entity/Q621322","name":"Power Macintosh"},{"id":"http://www.wikidata.org/entity/Q3046263","name":"Exelvision EXL 100"},{"id":"http://www.wikidata.org/entity/Q3480628","name":"Seta 1st Generation"},{"id":"http://www.wikidata.org/entity/Q3509103","name":"System SSV"},{"id":"http://www.wikidata.org/entity/Q1196518","name":"Arcadia 2001"},{"id":"http://www.wikidata.org/entity/Q17042679","name":"Oric"},{"id":"http://www.wikidata.org/entity/Q64152883","name":"Thomson MO"},{"id":"http://www.wikidata.org/entity/Q981935","name":"Amstrad GX4000"},{"id":"http://www.wikidata.org/entity/Q1324477","name":"Triforce"},{"id":"http://www.wikidata.org/entity/Q1568240","name":"PDP-10"},{"id":"http://www.wikidata.org/entity/Q3296053","name":"Marvin's Maze"},{"id":"http://www.wikidata.org/entity/Q3525757","name":"Thomson MO6"},{"id":"http://www.wikidata.org/entity/Q3278269","name":"Main Event"},{"id":"http://www.wikidata.org/entity/Q491640","name":"Family Computer"},{"id":"http://www.wikidata.org/entity/Q114834512","name":"miniStation"},{"id":"http://www.wikidata.org/entity/Q2818040","name":"SNK 68K Based Hardware"},{"id":"http://www.wikidata.org/entity/Q7886241","name":"Sega System C-2"},{"id":"http://www.wikidata.org/entity/Q1136254","name":"BlueSky Software"},{"id":"http://www.wikidata.org/entity/Q1198088","name":"Playdia"},{"id":"http://www.wikidata.org/entity/Q29578134","name":"NMS Software"},{"id":"http://www.wikidata.org/entity/Q3509087","name":"Namco System 246"},{"id":"http://www.wikidata.org/entity/Q843916","name":"Naomi 2"},{"id":"http://www.wikidata.org/entity/Q1067380","name":"Sega Titan Video"},{"id":"http://www.wikidata.org/entity/Q2428727","name":"Thomson TO7-70"},{"id":"http://www.wikidata.org/entity/Q1369174","name":"Sega NAOMI"},{"id":"http://www.wikidata.org/entity/Q941283","name":"S60"},{"id":"http://www.wikidata.org/entity/Q1995656","name":"Series 40"},{"id":"http://www.wikidata.org/entity/Q20965967","name":"tvOS"},{"id":"http://www.wikidata.org/entity/Q1140676","name":"Cassette Vision"},{"id":"http://www.wikidata.org/entity/Q3525763","name":"Thomson TO9"},{"id":"http://www.wikidata.org/entity/Q284305","name":"i-mode"},{"id":"http://www.wikidata.org/entity/Q182933","name":"x86"},{"id":"http://www.wikidata.org/entity/Q3437707","name":"Rock-ola"},{"id":"http://www.wikidata.org/entity/Q3509069","name":"Namco System 10"},{"id":"http://www.wikidata.org/entity/Q34825","name":"Windows Phone 8"},{"id":"http://www.wikidata.org/entity/Q843878","name":"Sega System 18"},{"id":"http://www.wikidata.org/entity/Q2916338","name":"Game Boy family"},{"id":"http://www.wikidata.org/entity/Q3410053","name":"Psycho Soldier"},{"id":"http://www.wikidata.org/entity/Q22645","name":"smartphone"},{"id":"http://www.wikidata.org/entity/Q602253","name":"Sinclair QL"},{"id":"http://www.wikidata.org/entity/Q2981066","name":"Taito Type X"},{"id":"http://www.wikidata.org/entity/Q24159643","name":"Raiden II"},{"id":"http://www.wikidata.org/entity/Q3512184","name":"TI-83 Plus"},{"id":"http://www.wikidata.org/entity/Q1067213","name":"Chihiro"},{"id":"http://www.wikidata.org/entity/Q3124730","name":"HAL 21"},{"id":"http://www.wikidata.org/entity/Q118163709","name":"Amstrad CPC Plus"},{"id":"http://www.wikidata.org/entity/Q135811","name":"Z-machine"},{"id":"http://www.wikidata.org/entity/Q495432","name":"Windows 3.1"},{"id":"http://www.wikidata.org/entity/Q251","name":"Java"},{"id":"http://www.wikidata.org/entity/Q8018077","name":"Super Cassette Vision"},{"id":"http://www.wikidata.org/entity/Q2634041","name":"CP System III"},{"id":"http://www.wikidata.org/entity/Q3030992","name":"Sega System 32"},{"id":"http://www.wikidata.org/entity/Q1575","name":"Internet Explorer"},{"id":"http://www.wikidata.org/entity/Q2377817","name":"ZN-2"},{"id":"http://www.wikidata.org/entity/Q34349","name":"IBM Personal Computer XT"},{"id":"http://www.wikidata.org/entity/Q956685","name":"Freedom of Mobile Multimedia Access"},{"id":"http://www.wikidata.org/entity/Q2701019","name":"IBM 7090"},{"id":"http://www.wikidata.org/entity/Q7670336","name":"TIA-MC-1"},{"id":"http://www.wikidata.org/entity/Q3574370","name":"ZN-1"},{"id":"http://www.wikidata.org/entity/Q356","name":"Google+"},{"id":"http://www.wikidata.org/entity/Q654114","name":"Macintosh 512K"},{"id":"http://www.wikidata.org/entity/Q116634","name":"online game"},{"id":"http://www.wikidata.org/entity/Q20718","name":"Samsung Electronics"},{"id":"http://www.wikidata.org/entity/Q239749","name":"Maemo"},{"id":"http://www.wikidata.org/entity/Q196561","name":"Kindle Fire"},{"id":"http://www.wikidata.org/entity/Q375913","name":"WebGL"},{"id":"http://www.wikidata.org/entity/Q241874","name":"MeeGo"},{"id":"http://www.wikidata.org/entity/Q941818","name":"handheld game console"},{"id":"http://www.wikidata.org/entity/Q609306","name":"Tizen"},{"id":"http://www.wikidata.org/entity/Q1052025","name":"PlayStation Store"},{"id":"http://www.wikidata.org/entity/Q7049700","name":"Nook Color"},{"id":"http://www.wikidata.org/entity/Q2160367","name":"BlackBerry Tablet OS"},{"id":"http://www.wikidata.org/entity/Q4530921","name":"Elektronika IM"},{"id":"http://www.wikidata.org/entity/Q15995436","name":"Roku"},{"id":"http://www.wikidata.org/entity/Q3525762","name":"Thomson TO8"},{"id":"http://www.wikidata.org/entity/Q7907719","name":"V Cast"},{"id":"http://www.wikidata.org/entity/Q8024430","name":"Windows Mobile 2003"},{"id":"http://www.wikidata.org/entity/Q114811722","name":"nD"},{"id":"http://www.wikidata.org/entity/Q1135858","name":"Flash Video"},{"id":"http://www.wikidata.org/entity/Q1475303","name":"Microvision"},{"id":"http://www.wikidata.org/entity/Q740626","name":"Atari TT030"},{"id":"http://www.wikidata.org/entity/Q3869483","name":"PC-8000 series"},{"id":"http://www.wikidata.org/entity/Q109359720","name":"NEC PC-9801 series"},{"id":"http://www.wikidata.org/entity/Q9479","name":"iPod"},{"id":"http://www.wikidata.org/entity/Q3509079","name":"Namco System 22"},{"id":"http://www.wikidata.org/entity/Q5082128","name":"mobile device"},{"id":"http://www.wikidata.org/entity/Q909005","name":"Gizmondo"},{"id":"http://www.wikidata.org/entity/Q576341","name":"DoJa"},{"id":"http://www.wikidata.org/entity/Q4485157","name":"PC game"},{"id":"http://www.wikidata.org/entity/Q914171","name":"Kaypro"},{"id":"http://www.wikidata.org/entity/Q1140061","name":"Xerox Alto"},{"id":"http://www.wikidata.org/entity/Q5294","name":"DVD"},{"id":"http://www.wikidata.org/entity/Q2043357","name":"Acorn Atom"},{"id":"http://www.wikidata.org/entity/Q7928734","name":"View-Master Interactive Vision"},{"id":"http://www.wikidata.org/entity/Q1007089","name":"GREE"},{"id":"http://www.wikidata.org/entity/Q4011418","name":"Videotel"},{"id":"http://www.wikidata.org/entity/Q479882","name":"OpenVMS"},{"id":"http://www.wikidata.org/entity/Q264627","name":"Glulx"},{"id":"http://www.wikidata.org/entity/Q78928288","name":"Intellivision Amico"},{"id":"http://www.wikidata.org/entity/Q992968","name":"mobile telephony"},{"id":"http://www.wikidata.org/entity/Q853958","name":"NTT DoCoMo"},{"id":"http://www.wikidata.org/entity/Q904519","name":"Mac OS 9"},{"id":"http://www.wikidata.org/entity/Q4835082","name":"BBS door"},{"id":"http://www.wikidata.org/entity/Q676052","name":"QNX"},{"id":"http://www.wikidata.org/entity/Q2475188","name":"Super A'Can"},{"id":"http://www.wikidata.org/entity/Q80031078","name":"IBM PC"},{"id":"http://www.wikidata.org/entity/Q621254","name":"Apple II Plus"},{"id":"http://www.wikidata.org/entity/Q2041444","name":"handheld TV game"},{"id":"http://www.wikidata.org/entity/Q3011188","name":"DECSYSTEM-20"},{"id":"http://www.wikidata.org/entity/Q1115883","name":"Commodore 64 Games System"},{"id":"http://www.wikidata.org/entity/Q10854461","name":"TurboGrafx-CD"},{"id":"http://www.wikidata.org/entity/Q907531","name":"GP2X"},{"id":"http://www.wikidata.org/entity/Q7969857","name":"WarpOS"},{"id":"http://www.wikidata.org/entity/Q75","name":"Internet"},{"id":"http://www.wikidata.org/entity/Q1323782","name":"Nintendo VS. System"},{"id":"http://www.wikidata.org/entity/Q623459","name":"Silicon Graphics"},{"id":"http://www.wikidata.org/entity/Q324610","name":"Intel 8080"},{"id":"http://www.wikidata.org/entity/Q14523564","name":"TRS-80"},{"id":"http://www.wikidata.org/entity/Q4812841","name":"Atari System"},{"id":"http://www.wikidata.org/entity/Q373442","name":"web browser engine"},{"id":"http://www.wikidata.org/entity/Q63777286","name":"Oculus Quest"},{"id":"http://www.wikidata.org/entity/Q99620218","name":"Quest 2"},{"id":"http://www.wikidata.org/entity/Q968545","name":"Mattel Aquarius"},{"id":"http://www.wikidata.org/entity/Q1122074","name":"CompuServe"},{"id":"http://www.wikidata.org/entity/Q274582","name":"Palm OS"},{"id":"http://www.wikidata.org/entity/Q442392","name":"Namco System 12"},{"id":"http://www.wikidata.org/entity/Q1894281","name":"Smaky"},{"id":"http://www.wikidata.org/entity/Q767457","name":"SkillGround"},{"id":"http://www.wikidata.org/entity/Q11238715","name":"PIECE"},{"id":"http://www.wikidata.org/entity/Q1243971","name":"R3000"},{"id":"http://www.wikidata.org/entity/Q1053294","name":"Fairchild Channel F"},{"id":"http://www.wikidata.org/entity/Q30277463","name":"pachinko slot machine"},{"id":"http://www.wikidata.org/entity/Q15282750","name":"Windows Phone 8.1"},{"id":"http://www.wikidata.org/entity/Q16081092","name":"NEC PC-8001"},{"id":"http://www.wikidata.org/entity/Q167784","name":"GNOME Web"},{"id":"http://www.wikidata.org/entity/Q1066773","name":"PMD 85"},{"id":"http://www.wikidata.org/entity/Q844362","name":"PC-98"},{"id":"http://www.wikidata.org/entity/Q136469","name":"Amazon Kindle"},{"id":"http://www.wikidata.org/entity/Q63986220","name":"HarmonyOS"},{"id":"http://www.wikidata.org/entity/Q17424","name":"Windows RT"},{"id":"http://www.wikidata.org/entity/Q1759168","name":"Pokémon Mini"},{"id":"http://www.wikidata.org/entity/Q4686254","name":"Advanced Pico Beena"},{"id":"http://www.wikidata.org/entity/Q18012472","name":"watchOS"},{"id":"http://www.wikidata.org/entity/Q576901","name":"Didaktik"},{"id":"http://www.wikidata.org/entity/Q7827636","name":"Toshiba Pasopia 7"},{"id":"http://www.wikidata.org/entity/Q11215","name":"Windows 7"},{"id":"http://www.wikidata.org/entity/Q10370979","name":"Sharp MZ-2000"},{"id":"http://www.wikidata.org/entity/Q1140931","name":"PlayStation Mobile"},{"id":"http://www.wikidata.org/entity/Q2846919","name":"Android Ice Cream Sandwich"},{"id":"http://www.wikidata.org/entity/Q757617","name":"Atomiswave"},{"id":"http://www.wikidata.org/entity/Q3111078","name":"Nuon"},{"id":"http://www.wikidata.org/entity/Q42979","name":"BASIC"},{"id":"http://www.wikidata.org/entity/Q66712951","name":"Xbox One"},{"id":"http://www.wikidata.org/entity/Q7096284","name":"web platform"},{"id":"http://www.wikidata.org/entity/Q64794117","name":"Microtex 666"},{"id":"http://www.wikidata.org/entity/Q190685","name":"PC"},{"id":"http://www.wikidata.org/entity/Q351020","name":"KC 85"},{"id":"http://www.wikidata.org/entity/Q116933","name":"VK"},{"id":"http://www.wikidata.org/entity/Q836661","name":"pachinko"},{"id":"http://www.wikidata.org/entity/Q960616","name":"VAX"},{"id":"http://www.wikidata.org/entity/Q21436386","name":"Namco System ES3"},{"id":"http://www.wikidata.org/entity/Q1315930","name":"PC-1512"},{"id":"http://www.wikidata.org/entity/Q3356276","name":"Oric Telestrat"},{"id":"http://www.wikidata.org/entity/Q1343889","name":"Mac OS 8"},{"id":"http://www.wikidata.org/entity/Q907311","name":"Netflix"},{"id":"http://www.wikidata.org/entity/Q1108054","name":"Coleco Adam"},{"id":"http://www.wikidata.org/entity/Q10370980","name":"Sharp MZ-2500"},{"id":"http://www.wikidata.org/entity/Q399128","name":"Browser"},{"id":"http://www.wikidata.org/entity/Q675128","name":"Ferranti Mark 1"},{"id":"http://www.wikidata.org/entity/Q1322287","name":"Sega SC-3000"},{"id":"http://www.wikidata.org/entity/Q36774","name":"web page"},{"id":"http://www.wikidata.org/entity/Q926446","name":"Timex Sinclair 2068"},{"id":"http://www.wikidata.org/entity/Q1343048","name":"Amiga Enhanced Chip Set"},{"id":"http://www.wikidata.org/entity/Q1969923","name":"Original Chip Set"},{"id":"http://www.wikidata.org/entity/Q65227540","name":"ALLS HX2"},{"id":"http://www.wikidata.org/entity/Q17623282","name":"Namco System 256"},{"id":"http://www.wikidata.org/entity/Q744987","name":"Odyssey"},{"id":"http://www.wikidata.org/entity/Q34264","name":"Berkeley Software Distribution"},{"id":"http://www.wikidata.org/entity/Q63993524","name":"Playdate"},{"id":"http://www.wikidata.org/entity/Q8076","name":"video game console"},{"id":"http://www.wikidata.org/entity/Q1265495","name":"IBM 700/7000 series"},{"id":"http://www.wikidata.org/entity/Q58636917","name":"BSD"},{"id":"http://www.wikidata.org/entity/Q3459526","name":"SGI Onyx"},{"id":"http://www.wikidata.org/entity/Q11368","name":"Unix"},{"id":"http://www.wikidata.org/entity/Q3884","name":"Amazon"},{"id":"http://www.wikidata.org/entity/Q52229854","name":"Android emulator"},{"id":"http://www.wikidata.org/entity/Q11796261","name":"Odra 1003"},{"id":"http://www.wikidata.org/entity/Q215448","name":"Haiku"},{"id":"http://www.wikidata.org/entity/Q65458682","name":"Nintendo Switch Lite"},{"id":"http://www.wikidata.org/entity/Q1404685","name":"Video Genie"},{"id":"http://www.wikidata.org/entity/Q57741692","name":"Dragon 32"},{"id":"http://www.wikidata.org/entity/Q343682","name":"Action Max"},{"id":"http://www.wikidata.org/entity/Q104531140","name":"KFConsole"},{"id":"http://www.wikidata.org/entity/Q6509976","name":"Leapster"},{"id":"http://www.wikidata.org/entity/Q66712869","name":"Xbox One S"},{"id":"http://www.wikidata.org/entity/Q30700179","name":"Xbox One X"},{"id":"http://www.wikidata.org/entity/Q250","name":"computer keyboard"},{"id":"http://www.wikidata.org/entity/Q26884850","name":"smart speaker"},{"id":"http://www.wikidata.org/entity/Q28456260","name":"PICO-8"},{"id":"http://www.wikidata.org/entity/Q86835955","name":"VR Sense"},{"id":"http://www.wikidata.org/entity/Q46441","name":"Cascading Style Sheets"},{"id":"http://www.wikidata.org/entity/Q861508","name":"Chromebook"},{"id":"http://www.wikidata.org/entity/Q11330849","name":"Video Challenger"},{"id":"http://www.wikidata.org/entity/Q51593195","name":"Nelsonic Game Watch"},{"id":"http://www.wikidata.org/entity/Q15961745","name":"Wear OS"},{"id":"http://www.wikidata.org/entity/Q22907849","name":"Discord"},{"id":"http://www.wikidata.org/entity/Q805385","name":"Bally Astrocade"},{"id":"http://www.wikidata.org/entity/Q17462601","name":"Atari Flagstaff"},{"id":"http://www.wikidata.org/entity/Q1252773","name":"GNU Emacs"},{"id":"http://www.wikidata.org/entity/Q732683","name":"Watara Supervision"},{"id":"http://www.wikidata.org/entity/Q7695504","name":"Tektronix 405x"},{"id":"http://www.wikidata.org/entity/Q1904276","name":"Pocket Dream Console"},{"id":"http://www.wikidata.org/entity/Q692989","name":"Roblox"},{"id":"http://www.wikidata.org/entity/Q16638273","name":"GCW Zero"},{"id":"http://www.wikidata.org/entity/Q17042614","name":"Neo Geo"},{"id":"http://www.wikidata.org/entity/Q2156242","name":"Pachi-Slo"},{"id":"http://www.wikidata.org/entity/Q5227493","name":"Datasaab D2"},{"id":"http://www.wikidata.org/entity/Q7967355","name":"Wang 2200"},{"id":"http://www.wikidata.org/entity/Q14743726","name":"Nintendo 2DS"},{"id":"http://www.wikidata.org/entity/Q3518305","name":"Terebikko"},{"id":"http://www.wikidata.org/entity/Q11232199","name":"MSX 2+"},{"id":"http://www.wikidata.org/entity/Q17148949","name":"Virtuality"},{"id":"http://www.wikidata.org/entity/Q1908959","name":"Matra Alice"},{"id":"http://www.wikidata.org/entity/Q6886593","name":"Mobage"},{"id":"http://www.wikidata.org/entity/Q73368","name":"online"},{"id":"http://www.wikidata.org/entity/Q41168744","name":"Atari VCS"},{"id":"http://www.wikidata.org/entity/Q112027954","name":"Pokitto"},{"id":"http://www.wikidata.org/entity/Q112943324","name":"Ocelot Arcade System"},{"id":"http://www.wikidata.org/entity/Q114543594","name":"CircuitMess Nibble"},{"id":"http://www.wikidata.org/entity/Q114544608","name":"CircuitMess Ringo"},{"id":"http://www.wikidata.org/entity/Q114562179","name":"ESPboy"},{"id":"http://www.wikidata.org/entity/Q2982516","name":"Nintendo Entertainment System hardware clone"},{"id":"http://www.wikidata.org/entity/Q112872459","name":"Meggy Jr RGB"},{"id":"http://www.wikidata.org/entity/Q941558","name":"PSP Go"},{"id":"http://www.wikidata.org/entity/Q3814081","name":"app store"},{"id":"http://www.wikidata.org/entity/Q10421167","name":"Atari XE"},{"id":"http://www.wikidata.org/entity/Q15613992","name":"arcade-style video game"},{"id":"http://www.wikidata.org/entity/Q491546","name":"Windows 3.0"},{"id":"http://www.wikidata.org/entity/Q466","name":"World Wide Web"},{"id":"http://www.wikidata.org/entity/Q1037185","name":"HP 95LX"},{"id":"http://www.wikidata.org/entity/Q56473777","name":"TIC-80"},{"id":"http://www.wikidata.org/entity/Q76193768","name":"Nokia Asha"},{"id":"http://www.wikidata.org/entity/Q468451","name":"Intel 8085"},{"id":"http://www.wikidata.org/entity/Q865817","name":"Java applet"},{"id":"http://www.wikidata.org/entity/Q3648618","name":"CDC 1604"},{"id":"http://www.wikidata.org/entity/Q14777661","name":"BBS software for the Texas Instruments TI-99/4A"},{"id":"http://www.wikidata.org/entity/Q506908","name":"Sord M5"},{"id":"http://www.wikidata.org/entity/Q526646","name":"SV-328"},{"id":"http://www.wikidata.org/entity/Q724174","name":"MicroBee"},{"id":"http://www.wikidata.org/entity/Q733136","name":"Mega Duck"},{"id":"http://www.wikidata.org/entity/Q746047","name":"Memotech MTX"},{"id":"http://www.wikidata.org/entity/Q2271641","name":"SV-318"},{"id":"http://www.wikidata.org/entity/Q7119740","name":"PMI-80"},{"id":"http://www.wikidata.org/entity/Q9132410","name":"ZX Spectrum 128K+"},{"id":"http://www.wikidata.org/entity/Q29271252","name":"ZX Spectrum Next"},{"id":"http://www.wikidata.org/entity/Q16011703","name":"PlayStation VR"},{"id":"http://www.wikidata.org/entity/Q107944338","name":"PlayStation VR2"},{"id":"http://www.wikidata.org/entity/Q12042631","name":"Ondra"},{"id":"http://www.wikidata.org/entity/Q3056443","name":"Atari XL"},{"id":"http://www.wikidata.org/entity/Q123284188","name":"BYOND"}]